wavefront_lambda/__init__.py
wavefront_lambda-0.9.4.dist-info/METADATA
wavefront_lambda-0.9.4.dist-info/RECORD
wavefront_lambda-0.9.4.dist-info/WHEEL
wavefront_lambda-0.9.4.dist-info/top_level.txt
