Metadata-Version: 2.1
Name: wavefront-lambda
Version: 0.9.4
Summary: Wavefront Python Wrapper for AWS Lambda
Home-page: https://github.com/wavefrontHQ/wavefront-lambda-python
Author: UNKNOWN
Author-email: UNKNOWN
License: UNKNOWN
Keywords: Wavefront Lambda,Wavefront
Platform: UNKNOWN
Requires-Dist: wavefront-pyformance (>=0.9.2)
